{
  "version": 1,
  "copyright": "Cards, Decks and Hands Sprites were originally from Paradise Station (https://github.com/ParadiseSS13/Paradise) and modified by VictorJob. All Glorm Fish modifications and art by Nugget (aka Space_Nugget)",
  "license": "CC-BY-SA-3.0",
  "size": {
    "x": 32,
    "y": 32
  },
  "states": [
    {
      "name": "glormfish_hand1"
    },
    {
      "name": "glormfish_hand2"
    },
    {
      "name": "glormfish_hand3"
    },
    {
      "name": "glormfish_hand4"
    },
    {
      "name": "glormfish_hand5"
    },
    {
      "name": "deck_glormfish_empty"
    },
    {
      "name": "deck_glormfish_full"
    },
    {
      "name": "deck_glormfish_half"
    },
    {
      "name": "deck_glormfish_low"
    },
    {
        "name": "glormfish_box"
    },
    {
        "name": "glormfish_box_open"
    },
    {
        "name": "singlecard_down_glormfish"
    },
    {
        "name": "card_1_buuzi"
    },
    {
        "name": "card_2_buuzi"
    },
    {
        "name": "card_3_buuzi"
    },
    {
        "name": "card_4_buuzi"
    },
    {
        "name": "card_1_carp"
    },
    {
        "name": "card_2_carp"
    },
    {
        "name": "card_3_carp"
    },
    {
        "name": "card_4_carp"
    },
    {
        "name": "card_1_cheezi"
    },
    {
        "name": "card_2_cheezi"
    },
    {
        "name": "card_3_cheezi"
    },
    {
        "name": "card_4_cheezi"
    },
    {
        "name": "card_1_finfin"
    },
    {
        "name": "card_2_finfin"
    },
    {
        "name": "card_3_finfin"
    },
    {
        "name": "card_4_finfin"
    },
    {
        "name": "card_1_frog"
    },
    {
        "name": "card_2_frog"
    },
    {
        "name": "card_3_frog"
    },
    {
        "name": "card_4_frog"
    },
    {
        "name": "card_1_hggu"
    },
    {
        "name": "card_2_hggu"
    },
    {
        "name": "card_3_hggu"
    },
    {
        "name": "card_4_hggu"
    },
    {
        "name": "card_1_mothroach"
    },
    {
        "name": "card_2_mothroach"
    },
    {
        "name": "card_3_mothroach"
    },
    {
        "name": "card_4_mothroach"
    },
    {
        "name": "card_1_doomba"
    },
    {
        "name": "card_2_doomba"
    },
    {
        "name": "card_3_doomba"
    },
    {
        "name": "card_4_doomba"
    },
    {
        "name": "card_1_pig"
    },
    {
        "name": "card_2_pig"
    },
    {
        "name": "card_3_pig"
    },
    {
        "name": "card_4_pig"
    },
    {
        "name": "card_1_ku"
    },
    {
        "name": "card_2_ku"
    },
    {
        "name": "card_3_ku"
    },
    {
        "name": "card_4_ku"
    },
    {
        "name": "card_1_snail"
    },
    {
        "name": "card_2_snail"
    },
    {
        "name": "card_3_snail"
    },
    {
        "name": "card_4_snail"
    },
    {
        "name": "card_1_sqoshi"
    },
    {
        "name": "card_2_sqoshi"
    },
    {
        "name": "card_3_sqoshi"
    },
    {
        "name": "card_4_sqoshi"
    },
    {
        "name": "card_1_tsshisuni"
    },
    {
        "name": "card_2_tsshisuni"
    },
    {
        "name": "card_3_tsshisuni"
    },
    {
        "name": "card_4_tsshisuni"
    },
    {
        "name": "card_1_UGGH"
    },
    {
        "name": "card_2_UGGH"
    },
    {
        "name": "card_3_UGGH"
    },
    {
        "name": "card_4_UGGH"
    }
  ]
}
